gias3.musculoskeletal-3.0.1-py3.11-nspkg.pth
gias3/musculoskeletal/__init__.py
gias3/musculoskeletal/fw_femur_measurements.py
gias3/musculoskeletal/fw_femur_model_data.py
gias3/musculoskeletal/fw_model_landmarks.py
gias3/musculoskeletal/fw_pelvis_measurements.py
gias3/musculoskeletal/fw_pelvis_model_data.py
gias3/musculoskeletal/mocap_landmark_preprocess.py
gias3/musculoskeletal/model_alignment.py
gias3/musculoskeletal/model_alignment_multi.py
gias3/musculoskeletal/osim.py
gias3/musculoskeletal/pelvis_hjc_estimation.py
gias3/musculoskeletal/viewfemurmeasurements.py
gias3/musculoskeletal/bonemodels/__init__.py
gias3/musculoskeletal/bonemodels/bonemodels.py
gias3/musculoskeletal/bonemodels/lowerlimbatlas.py
gias3/musculoskeletal/bonemodels/lowerlimbatlasfit.py
gias3/musculoskeletal/bonemodels/lowerlimbatlasfit2side.py
gias3/musculoskeletal/bonemodels/lowerlimbatlasfitscaling.py
gias3/musculoskeletal/bonemodels/modelcore.py
gias3.musculoskeletal-3.0.1.dist-info/LICENSE
gias3.musculoskeletal-3.0.1.dist-info/METADATA
gias3.musculoskeletal-3.0.1.dist-info/WHEEL
gias3.musculoskeletal-3.0.1.dist-info/namespace_packages.txt
gias3.musculoskeletal-3.0.1.dist-info/top_level.txt
gias3.musculoskeletal-3.0.1.dist-info/RECORD
